streamlit_mic_recorder/__init__.py
streamlit_mic_recorder/frontend/build/asset-manifest.json
streamlit_mic_recorder/frontend/build/bootstrap.min.css
streamlit_mic_recorder/frontend/build/index.html
streamlit_mic_recorder/frontend/build/static/css/main.27af0a20.css
streamlit_mic_recorder/frontend/build/static/css/main.27af0a20.css.map
streamlit_mic_recorder/frontend/build/static/js/main.010058c4.js
streamlit_mic_recorder/frontend/build/static/js/main.010058c4.js.LICENSE.txt
streamlit_mic_recorder/frontend/build/static/js/main.010058c4.js.map
streamlit_mic_recorder/frontend/build/static/js/main.78733ce9.js
streamlit_mic_recorder/frontend/build/static/js/main.78733ce9.js.LICENSE.txt
streamlit_mic_recorder/frontend/build/static/js/main.78733ce9.js.map
streamlit_mic_recorder/frontend/build/static/js/main.7b8c1ece.js
streamlit_mic_recorder/frontend/build/static/js/main.7b8c1ece.js.LICENSE.txt
streamlit_mic_recorder/frontend/build/static/js/main.7b8c1ece.js.map
streamlit_mic_recorder/frontend/build/static/js/main.7d07c2c9.js
streamlit_mic_recorder/frontend/build/static/js/main.7d07c2c9.js.LICENSE.txt
streamlit_mic_recorder/frontend/build/static/js/main.7d07c2c9.js.map
streamlit_mic_recorder/frontend/build/static/js/main.c5edc685.js
streamlit_mic_recorder/frontend/build/static/js/main.c5edc685.js.LICENSE.txt
streamlit_mic_recorder/frontend/build/static/js/main.c5edc685.js.map
streamlit_mic_recorder/frontend/build/static/js/main.e94efa70.js
streamlit_mic_recorder/frontend/build/static/js/main.e94efa70.js.LICENSE.txt
streamlit_mic_recorder/frontend/build/static/js/main.e94efa70.js.map
streamlit_mic_recorder/frontend/build/static/js/main.fe25ed90.js
streamlit_mic_recorder/frontend/build/static/js/main.fe25ed90.js.LICENSE.txt
streamlit_mic_recorder/frontend/build/static/js/main.fe25ed90.js.map
streamlit_mic_recorder_custom-0.0.2.dist-info/LICENSE
streamlit_mic_recorder_custom-0.0.2.dist-info/METADATA
streamlit_mic_recorder_custom-0.0.2.dist-info/WHEEL
streamlit_mic_recorder_custom-0.0.2.dist-info/top_level.txt
streamlit_mic_recorder_custom-0.0.2.dist-info/RECORD
