Metadata-Version: 2.1
Name: streamlit_mic_recorder_custom
Version: 0.0.2
Summary: Streamlit component that allows to record mono audio from the user's microphone, and/or perform speech recognition directly.
Home-page: https://github.com/misterkevinski/streamlit-mic-recorder
Author: Kevin Beck
Author-email: misterkevinski@gmail.com
Requires-Python: >=3.7
License-File: LICENSE
Requires-Dist: streamlit>=0.63
Requires-Dist: SpeechRecognition
